vaultapi_client/__init__.py
vaultapi_client/aws.py
vaultapi_client/config.py
vaultapi_client/exceptions.py
vaultapi_client/main.py
vaultapi_client/session.py
vaultapi_client/transit.py
vaultapi_client/util.py
vaultapi_client-0.2.0.dist-info/licenses/LICENSE
vaultapi_client-0.2.0.dist-info/METADATA
vaultapi_client-0.2.0.dist-info/WHEEL
vaultapi_client-0.2.0.dist-info/entry_points.txt
vaultapi_client-0.2.0.dist-info/top_level.txt
vaultapi_client-0.2.0.dist-info/RECORD
