Metadata-Version: 2.4
Name: VaultAPI-Client
Version: 0.2.0
Summary: Client application for VaultAPI Server
Author-email: Vignesh Rao <svignesh1793@gmail.com>
License: MIT License
Project-URL: Homepage, https://github.com/thevickypedia/VaultAPI-Client-python
Project-URL: Source, https://github.com/thevickypedia/VaultAPI-Client-python
Keywords: vaultapi,vault,fastapi,sqlite3,fernet
Classifier: License :: OSI Approved :: MIT License
Classifier: Programming Language :: Python :: 3
Classifier: Development Status :: 5 - Production/Stable
Classifier: Operating System :: OS Independent
Classifier: Topic :: Security :: Cryptography
Requires-Python: >=3.10
License-File: LICENSE
Provides-Extra: dev
Requires-Dist: pre-commit; extra == "dev"
Provides-Extra: aws
Requires-Dist: boto3==1.36.*; extra == "aws"
Dynamic: license-file
